Project_1/02_counter_dataflow/count_down_dataflow.v
/*
The count_down() module is a 4-bit down counter implemented using data flow.
@ author    Minh Khuu
@ date      2016.01.07
@ version   Project 1.2 =========== < 4-bit Asynchronous Down Counter [Dataflow] >

TYPE      |NAME       |WIDTH    |DESCRIPTION       
-----------------------------------------------------------------------------------
output    |out        |4 bit    |The 4-bit output, counts from 15 to 0 in decimal.
input     |reset      |1 bit    |The reset signal (active low).
input     |clk        |1 bit    |The clock for the system.

*/
module count_down_dataflow(out, reset, clk);

  /* Defining the output/input ports */
  output [3:0] out;
  input reset, clk;
  
  /* Wires for connection */
  wire [3:0] new_out;
  wire [3:0] not_out;

  /* Operation for each stage for the new state */
  assign new_out[0] = ~out[0];
  assign new_out[1] = ~(out[1] ^ out[0]);
  assign new_out[2] = (~out[2] & ~out[1] & ~out[0]) | (out[2] & (out[1] | out[0]));
  assign new_out[3] = (~out[3] & ~out[2] & ~out[1] & ~out[0]) | (out[3] & (out[2] | out[1] | out[0]));
  
  /* D_Flip_Flop for new state to present stage assignment */
  D_FF stage0 (.q(out[0]), .qBar(not_out[0]), .D(new_out[0]), .clk(clk), .rst(reset));
  D_FF stage1 (.q(out[1]), .qBar(not_out[1]), .D(new_out[1]), .clk(clk), .rst(reset));
  D_FF stage2 (.q(out[2]), .qBar(not_out[2]), .D(new_out[2]), .clk(clk), .rst(reset));
  D_FF stage3 (.q(out[3]), .qBar(not_out[3]), .D(new_out[3]), .clk(clk), .rst(reset));

endmodule

/*
The D_FF module is a D_Flip_Flop.  The code was given by James K. Peckol for EE371.

TYPE      |NAME       |WIDTH    |DESCRIPTION       
-----------------------------------------------------------------------------------
output    |q          |1 bit    |The present state.
output    |qBar       |1 bit    |The inverted present state.
input     |D          |1 bit    |The new state.
input     |clk        |1 bit    |The clock for the system.
input     |rst        |1 bit    |The reset signal (active low).
 */
module D_FF(q, qBar, D, clk, rst);

  /* Defining the output/input ports */
  input D, clk, rst;
  output q, qBar;
  reg q;
  
  /* retrieve inverted output */
  not n1 (qBar, q);
  
  /* update the present state with the next state */
  always@ (negedge rst or posedge clk) begin
  if(!rst)
    q <= 0;
  else
    q = D;
  end
  
endmodule

/* ---------------------------------------------------------------------------------------- */
/* ------------------------------------TEST BENCH------------------------------------------ */
/* ---------------------------------------------------------------------------------------- */

/*
The count_down_testBench module tests the count_down module. 
*/
module count_down_dataflow_testBench;

  /* Wires for testing */
  wire [3:0] out;
  wire reset, clk;
  
  /* declare instance of count_down module */
  count_down_dataflow dut (.out(out), .reset(reset), .clk(clk));
  
  /* declare instance of test module */
  count_down_dataflow_tester aTest (reset, clk, out);
  
  /* file for gtkwave */
  initial begin
    $dumpfile("____gtkwave____DATAFLOW____.vcd");
    $dumpvars(1, dut);
  end
  
endmodule

/*
The count_down_tester module generates the reset and clock signals for testing.
It also prints out, on stdout, the output and inputs of the count_down module.

TYPE      |NAME       |WIDTH    |DESCRIPTION       
-----------------------------------------------------------------------------------
output    |resetOut   |1 bit    |The generated reset signal for testing.
output    |clkOut     |1 bit    |The genereated clk signal for testing.
input     |out        |4 bit    |The output signal used for printing to stdout.
 */
module count_down_dataflow_tester(resetOut, clkOut, out);

  /* Defining the output/input ports */
  output reg resetOut, clkOut;
  input [3:0] out;
  
  /* Delay Constant */
  parameter DELAY = 10;
  integer i;
  
  /* Display information of ports to stdout */
  initial begin
    $display("\t resetOut \t clkOut \t out ");
    $monitor("\t %b\t %b \t %d", resetOut, clkOut, out);
  end
  
  /* Set values for ports w/ delays*/
  initial begin
    clkOut = 0;
    resetOut = 0; 
    #100 resetOut = 1; 
    for(i = 0; i < 26; i = i + 1) begin
      #DELAY clkOut = 1;
      #DELAY clkOut = 0;
    end
    resetOut = 0; 
    #100 $finish;
	end
  
endmodule

Project_1/02_counter_dataflow/____gtkwave____DATAFLOW____.vcd
$date
	Sat Jan 09 16:22:06 2016
$end
$version
	Icarus Verilog
$end
$timescale
	1s
$end
$scope module count_down_dataflow_testBench $end
$scope module dut $end
$var wire 1 ! clk $end
$var wire 1 " reset $end
$var wire 4 # out [3:0] $end
$var wire 4 $ not_out [3:0] $end
$var wire 4 % new_out [3:0] $end
$upscope $end
$upscope $end
$enddefinitions $end
#0
$dumpvars
b1111 %
b1111 $
b0 #
0"
0!
$end
#100
1"
#110
b1010 %
b0 $
b1111 #
1!
#120
0!
#130
b1001 %
b101 $
b1010 #
1!
#140
0!
#150
b1000 %
b110 $
b1001 #
1!
#160
0!
#170
b111 %
b111 $
b1000 #
1!
#180
0!
#190
b10 %
b1000 $
b111 #
1!
#200
0!
#210
b1 %
b1101 $
b10 #
1!
#220
0!
#230
b0 %
b1110 $
b1 #
1!
#240
0!
#250
b1111 %
b1111 $
b0 #
1!
#260
0!
#270
b1010 %
b0 $
b1111 #
1!
#280
0!
#290
b1001 %
b101 $
b1010 #
1!
#300
0!
#310
b1000 %
b110 $
b1001 #
1!
#320
0!
#330
b111 %
b111 $
b1000 #
1!
#340
0!
#350
b10 %
b1000 $
b111 #
1!
#360
0!
#370
b1 %
b1101 $
b10 #
1!
#380
0!
#390
b0 %
b1110 $
b1 #
1!
#400
0!
#410
b1111 %
b1111 $
b0 #
1!
#420
0!
#430
b1010 %
b0 $
b1111 #
1!
#440
0!
#450
b1001 %
b101 $
b1010 #
1!
#460
0!
#470
b1000 %
b110 $
b1001 #
1!
#480
0!
#490
b111 %
b111 $
b1000 #
1!
#500
0!
#510
b10 %
b1000 $
b111 #
1!
#520
0!
#530
b1 %
b1101 $
b10 #
1!
#540
0!
#550
b0 %
b1110 $
b1 #
1!
#560
0!
#570
b1111 %
b1111 $
b0 #
1!
#580
0!
#590
b1010 %
b0 $
b1111 #
1!
#600
0!
#610
b1001 %
b101 $
b1010 #
1!
#620
b1111 %
b1111 $
b0 #
0"
0!
