Project_1/03_counter_johnson/count_down_johnson_behavioural.v
/*
The count_down_johnson() module is a 4-bit johnson counter.
@ author    Ruchira Kulkarni
@ date      2016.01.07
@ version   Project 1.3 =========== < 4-bit Johnson Counter [Behavioural] >

TYPE      |NAME       |WIDTH    |DESCRIPTION       
-----------------------------------------------------------------------------------
output    |out        |4 bit    |The 4-bit output, counts from 15 to 0 in decimal.
input     |reset      |1 bit    |The reset signal (active low).
input     |clk        |1 bit    |The clock for the system.

*/
module count_down_johnson_behavioural(out, reset, clk);
  
  /* Defining the output/input ports */
  output reg [3:0] out;
	input reset, clk;

  /* Next state logic */
	always@ (negedge reset or posedge clk) begin
		if (!reset) out = 4'b0000;
		else begin
			out[3] <= ~out[0];
			out[2] <= out[3];
			out[1] <= out[2];
			out[0] <= out[1];
		end
	end
	
endmodule

/* ---------------------------------------------------------------------------------------- */
/* ------------------------------------TEST BENCH------------------------------------------ */
/* ---------------------------------------------------------------------------------------- */

/*
The count_down_testBench module tests the count_down module. 
*/
module count_down_johnson_behavioural_testBench;

  /* Wires for testing */
  wire [3:0] out;
  wire reset, clk;
  
  /* declare instance of count_down module */
  count_down_johnson_behavioural dut (.out(out), .reset(reset), .clk(clk));
  
  /* declare instance of test module */
  count_down_johnson_behavioural_tester aTest (reset, clk, out);
  
  /* file for gtkwave */
  initial begin
    $dumpfile("____gtkwave____BEHAVIOURAL____.vcd");
    $dumpvars(1, dut);
  end
  
endmodule

/*
The count_down_tester module generates the reset and clock signals for testing.
It also prints out, on stdout, the output and inputs of the count_down module.

TYPE      |NAME       |WIDTH    |DESCRIPTION       
-----------------------------------------------------------------------------------
output    |resetOut   |1 bit    |The generated reset signal for testing.
output    |clkOut     |1 bit    |The genereated clk signal for testing.
input     |out        |4 bit    |The output signal used for printing to stdout.
 */
module count_down_johnson_behavioural_tester(resetOut, clkOut, out);

  /* Defining the output/input ports */
  output reg resetOut, clkOut;
  input [3:0] out;
  
  /* Delay Constant */
  parameter DELAY = 10;
  integer i;
  
  /* Display information of ports to stdout */
  initial begin
    $display("\t resetOut \t clkOut \t out ");
    $monitor("\t %b\t %b \t %d", resetOut, clkOut, out);
  end
  
  /* Set values for ports w/ delays*/
  initial begin
    clkOut = 0;
    resetOut = 0; 
    #100 resetOut = 1; 
    for(i = 0; i < 26; i = i + 1) begin
      #DELAY clkOut = 1;
      #DELAY clkOut = 0;
    end
    resetOut = 0; 
    #100 $finish;
	end
  
endmodule

Project_1/03_counter_johnson/____gtkwave____BEHAVIOURAL____.vcd
$date
	Mon Jan 11 14:53:20 2016
$end
$version
	Icarus Verilog
$end
$timescale
	1s
$end
$scope module count_down_johnson_behavioural_testBench $end
$scope module dut $end
$var wire 1 ! clk $end
$var wire 1 " reset $end
$var reg 4 # out [3:0] $end
$upscope $end
$upscope $end
$enddefinitions $end
#0
$dumpvars
b0 #
0"
0!
$end
#10
1!
#20
0!
#30
1!
#40
0!
#50
1!
#60
0!
#70
1!
#80
0!
#90
1!
#100
0!
1"
#110
b1000 #
1!
#120
0!
#130
b1100 #
1!
#140
0!
#150
b1110 #
1!
#160
0!
#170
b1111 #
1!
#180
0!
#190
b111 #
1!
#200
0!
#210
b11 #
1!
#220
0!
#230
b1 #
1!
#240
0!
#250
b0 #
1!
#260
0!
#270
b1000 #
1!
#280
0!
#290
b1100 #
1!
#300
0!
#310
b1110 #
1!
#320
0!
#330
b1111 #
1!
#340
0!
#350
b111 #
1!
#360
0!
#370
b11 #
1!
#380
0!
#390
b1 #
1!
#400
0!
#410
b0 #
1!
#420
0!
#430
b1000 #
1!
#440
0!
#450
b1100 #
1!
#460
0!
#470
b1110 #
1!
#480
0!
#490
b1111 #
1!
#500
0!
#510
b111 #
1!
#520
0!
#530
b11 #
1!
#540
0!
#550
b1 #
1!
#560
0!
#570
b0 #
1!
#580
0!
#590
b1000 #
1!
#600
b0 #
0!
0"
#610
1!
#620
0!
#630
1!
#640
0!
#650
1!
#660
0!
#670
1!
#680
0!
#690
1!
#700
0!
1"
#710
b1000 #
1!
#720
0!
#730
b1100 #
1!
#740
0!
#750
b1110 #
1!
#760
0!
#770
b1111 #
1!
#780
0!
#790
b111 #
1!
#800
0!
#810
b11 #
1!
#820
0!
#830
b1 #
1!
#840
0!
#850
b0 #
1!
#860
0!
#870
b1000 #
1!
#880
0!
#890
b1100 #
1!
