Project_1/01_counter_structural/ripple_counter.v
module ripple_counter(out, reset, clk);
	input reset, clk;
	output[3:0] out;
	wire[3:0] inv_out;
	
	DFlipFlop flip3 (.q(out[3]), .qBar(inv_out[3]), .D(inv_out[3]), .clk(out[2]), .rst(reset));
	DFlipFlop flip2 (.q(out[2]), .qBar(inv_out[2]), .D(inv_out[2]), .clk(out[1]), .rst(reset));
	DFlipFlop flip1 (.q(out[1]), .qBar(inv_out[1]), .D(inv_out[1]), .clk(out[0]), .rst(reset));
	DFlipFlop flip0 (.q(out[0]), .qBar(inv_out[0]), .D(inv_out[0]), .clk(clk), .rst(reset));
endmodule

module DFlipFlop(q, qBar, D, clk, rst);
	input D, clk, rst;
	output q, qBar;
	
	reg q;
	not n1 (qBar, q);
	always@ (negedge rst or posedge clk) begin
		if(!rst)
			q = 0;
		else
			q = D;
	end
endmodule 

/* ---------------------------------------------------------------------------------------- */
/* ------------------------------------TEST BENCH------------------------------------------ */
/* ---------------------------------------------------------------------------------------- */

/*
The ripple_counter_testbench module tests the ripple_counter module. 
*/
module ripple_counter_testbench();
  /* Wires for testing */
  wire[3:0] out;
  wire reset, clk;
  
  /* declare instance of count_down module */
  ripple_counter dut (.out(out), .reset(reset), .clk(clk));
  
  /* declare instance of test module */
  ripple_counter_tester rippleTest (.resetOut(reset), .clkOut(clk), .out(out));
  
  /* file for gtkwave */
  initial begin
    $dumpfile("ripple_counter_gate.vcd");
    $dumpvars(1, dut);
  end
endmodule

/*
The ripple_counter_tester module generates the reset and clock signals for testing.
It also prints out, on stdout, the output and inputs of the ripple_counter module.

TYPE      |NAME       |WIDTH    |DESCRIPTION       
-----------------------------------------------------------------------------------
output    |resetOut   |1 bit    |The generated reset signal for testing.
output    |clkOut     |1 bit    |The genereated clk signal for testing.
input     |out        |4 bit    |The output signal used for printing to stdout.
 */
module ripple_counter_tester(resetOut, clkOut, out);
	/* Defining the output/input ports */
	output reg resetOut, clkOut;
	input[3:0] out;

	/* Delay Constant */
	parameter DELAY = 10;
	integer i;

	/* Display information of ports to stdout */
	initial begin
		$display("\t resetOut \t clkOut \t out ");
		$monitor("\t %b\t\t %b \t\t %d", resetOut, clkOut, out);
	end
	  
	parameter clk_period = 1000;
	initial clkOut = 1;
	always begin
		#(clk_period/2);
		clkOut = ~clkOut;
	end 

	initial begin
		resetOut <= 0; 			@(posedge clkOut);
		resetOut <= 1; 			@(posedge clkOut);
		
		for(i = 0; i < 100; i = i + 1) begin
			@(posedge clkOut);
		end
		
		$finish;
	end
  
endmodule

Project_1/01_counter_structural/ripple_counter_gate.vcd
$date
	Sat Jan 09 16:00:02 2016
$end
$version
	Icarus Verilog
$end
$timescale
	1s
$end
$scope module ripple_counter_testbench $end
$scope module dut $end
$var wire 1 ! reset $end
$var wire 4 " out [3:0] $end
$var wire 4 # inv_out [3:0] $end
$var wire 1 $ clk $end
$upscope $end
$upscope $end
$enddefinitions $end
#0
$dumpvars
1$
b1111 #
b0 "
0!
$end
#500
0$
#1000
1!
1$
#1500
0$
#2000
b0 #
b1111 "
1$
#2500
0$
#3000
b1 #
b1110 "
1$
#3500
0$
#4000
b10 #
b1101 "
1$
#4500
0$
#5000
b11 #
b1100 "
1$
#5500
0$
#6000
b100 #
b1011 "
1$
#6500
0$
#7000
b101 #
b1010 "
1$
#7500
0$
#8000
b110 #
b1001 "
1$
#8500
0$
#9000
b111 #
b1000 "
1$
#9500
0$
#10000
b1000 #
b111 "
1$
#10500
0$
#11000
b1001 #
b110 "
1$
#11500
0$
#12000
b1010 #
b101 "
1$
#12500
0$
#13000
b1011 #
b100 "
1$
#13500
0$
#14000
b1100 #
b11 "
1$
#14500
0$
#15000
b1101 #
b10 "
1$
#15500
0$
#16000
b1110 #
b1 "
1$
#16500
0$
#17000
b1111 #
b0 "
1$
#17500
0$
#18000
b0 #
b1111 "
1$
#18500
0$
#19000
b1 #
b1110 "
1$
#19500
0$
#20000
b10 #
b1101 "
1$
#20500
0$
#21000
b11 #
b1100 "
1$
#21500
0$
#22000
b100 #
b1011 "
1$
#22500
0$
#23000
b101 #
b1010 "
1$
#23500
0$
#24000
b110 #
b1001 "
1$
#24500
0$
#25000
b111 #
b1000 "
1$
#25500
0$
#26000
b1000 #
b111 "
1$
#26500
0$
#27000
b1001 #
b110 "
1$
#27500
0$
#28000
b1010 #
b101 "
1$
#28500
0$
#29000
b1011 #
b100 "
1$
#29500
0$
#30000
b1100 #
b11 "
1$
#30500
0$
#31000
b1101 #
b10 "
1$
#31500
0$
#32000
b1110 #
b1 "
1$
#32500
0$
#33000
b1111 #
b0 "
1$
#33500
0$
#34000
b0 #
b1111 "
1$
#34500
0$
#35000
b1 #
b1110 "
1$
#35500
0$
#36000
b10 #
b1101 "
1$
#36500
0$
#37000
b11 #
b1100 "
1$
#37500
0$
#38000
b100 #
b1011 "
1$
#38500
0$
#39000
b101 #
b1010 "
1$
#39500
0$
#40000
b110 #
b1001 "
1$
#40500
0$
#41000
b111 #
b1000 "
1$
#41500
0$
#42000
b1000 #
b111 "
1$
#42500
0$
#43000
b1001 #
b110 "
1$
#43500
0$
#44000
b1010 #
b101 "
1$
#44500
0$
#45000
b1011 #
b100 "
1$
#45500
0$
#46000
b1100 #
b11 "
1$
#46500
0$
#47000
b1101 #
b10 "
1$
#47500
0$
#48000
b1110 #
b1 "
1$
#48500
0$
#49000
b1111 #
b0 "
1$
#49500
0$
#50000
b0 #
b1111 "
1$
#50500
0$
#51000
b1 #
b1110 "
1$
#51500
0$
#52000
b10 #
b1101 "
1$
#52500
0$
#53000
b11 #
b1100 "
1$
#53500
0$
#54000
b100 #
b1011 "
1$
#54500
0$
#55000
b101 #
b1010 "
1$
#55500
0$
#56000
b110 #
b1001 "
1$
#56500
0$
#57000
b111 #
b1000 "
1$
#57500
0$
#58000
b1000 #
b111 "
1$
#58500
0$
#59000
b1001 #
b110 "
1$
#59500
0$
#60000
b1010 #
b101 "
1$
#60500
0$
#61000
b1011 #
b100 "
1$
#61500
0$
#62000
b1100 #
b11 "
1$
#62500
0$
#63000
b1101 #
b10 "
1$
#63500
0$
#64000
b1110 #
b1 "
1$
#64500
0$
#65000
b1111 #
b0 "
1$
#65500
0$
#66000
b0 #
b1111 "
1$
#66500
0$
#67000
b1 #
b1110 "
1$
#67500
0$
#68000
b10 #
b1101 "
1$
#68500
0$
#69000
b11 #
b1100 "
1$
#69500
0$
#70000
b100 #
b1011 "
1$
#70500
0$
#71000
b101 #
b1010 "
1$
#71500
0$
#72000
b110 #
b1001 "
1$
#72500
0$
#73000
b111 #
b1000 "
1$
#73500
0$
#74000
b1000 #
b111 "
1$
#74500
0$
#75000
b1001 #
b110 "
1$
#75500
0$
#76000
b1010 #
b101 "
1$
#76500
0$
#77000
b1011 #
b100 "
1$
#77500
0$
#78000
b1100 #
b11 "
1$
#78500
0$
#79000
b1101 #
b10 "
1$
#79500
0$
#80000
b1110 #
b1 "
1$
#80500
0$
#81000
b1111 #
b0 "
1$
#81500
0$
#82000
b0 #
b1111 "
1$
#82500
0$
#83000
b1 #
b1110 "
1$
#83500
0$
#84000
b10 #
b1101 "
1$
#84500
0$
#85000
b11 #
b1100 "
1$
#85500
0$
#86000
b100 #
b1011 "
1$
#86500
0$
#87000
b101 #
b1010 "
1$
#87500
0$
#88000
b110 #
b1001 "
1$
#88500
0$
#89000
b111 #
b1000 "
1$
#89500
0$
#90000
b1000 #
b111 "
1$
#90500
0$
#91000
b1001 #
b110 "
1$
#91500
0$
#92000
b1010 #
b101 "
1$
#92500
0$
#93000
b1011 #
b100 "
1$
#93500
0$
#94000
b1100 #
b11 "
1$
#94500
0$
#95000
b1101 #
b10 "
1$
#95500
0$
#96000
b1110 #
b1 "
1$
#96500
0$
#97000
b1111 #
b0 "
1$
#97500
0$
#98000
b0 #
b1111 "
1$
#98500
0$
#99000
b1 #
b1110 "
1$
#99500
0$
#100000
b10 #
b1101 "
1$
#100500
0$
#101000
b11 #
b1100 "
1$
#101500
0$
#102000
b100 #
b1011 "
1$
