Project_1/01_counter_structural/01_counter_structural__/ripple_counter.v
/*
The ripple_counter() module is a 4-bit down counter implemented using data flow.
@ author    Denny Ly
@ date      2016.01.07
@ version   Project 1.1 =========== < 4-bit Ripple Down Counter [Structural] >

TYPE      |NAME       |WIDTH    |DESCRIPTION       
-----------------------------------------------------------------------------------
output    |out        |4 bit    |The 4-bit output, counts from 15 to 0 in decimal.
input     |reset      |1 bit    |The reset signal (active low).
input     |clk        |1 bit    |The clock for the system.

*/
module ripple_counter(out, reset, clk);
	input reset, clk;
	output[3:0] out;
	wire[3:0] inv_out;
	
	DFlipFlop flip3 (.q(out[3]), .qBar(inv_out[3]), .D(inv_out[3]), .clk(out[2]), .rst(reset));
	DFlipFlop flip2 (.q(out[2]), .qBar(inv_out[2]), .D(inv_out[2]), .clk(out[1]), .rst(reset));
	DFlipFlop flip1 (.q(out[1]), .qBar(inv_out[1]), .D(inv_out[1]), .clk(out[0]), .rst(reset));
	DFlipFlop flip0 (.q(out[0]), .qBar(inv_out[0]), .D(inv_out[0]), .clk(clk), .rst(reset));
endmodule


/*
The DFlipFlop module is a D_Flip_Flop.  The code was given by James K. Peckol for EE371.

TYPE      |NAME       |WIDTH    |DESCRIPTION       
-----------------------------------------------------------------------------------
output    |q          |1 bit    |The present state.
output    |qBar       |1 bit    |The inverted present state.
input     |D          |1 bit    |The new state.
input     |clk        |1 bit    |The clock for the system.
input     |rst        |1 bit    |The reset signal (active low).
 */
module DFlipFlop(q, qBar, D, clk, rst);

  /* Defining the output/input ports */
  input D, clk, rst;
  output q, qBar;
  reg q;
  
  /* retrieve inverted output */
  not n1 (qBar, q);
  
  /* update the present state with the next state */
  always@ (negedge rst or posedge clk) begin
  if(!rst)
    q <= 0;
  else
    q = D;
  end
  
endmodule

/* ---------------------------------------------------------------------------------------- */
/* ------------------------------------TEST BENCH------------------------------------------ */
/* ---------------------------------------------------------------------------------------- */

/*
The ripple_counter_testbench module tests the ripple_counter module. 
*/
module ripple_counter_testbench();
  /* Wires for testing */
  wire[3:0] out;
  wire reset, clk;
  
  /* declare instance of count_down module */
  ripple_counter dut (.out(out), .reset(reset), .clk(clk));
  
  /* declare instance of test module */
  ripple_counter_tester rippleTest (.resetOut(reset), .clkOut(clk), .out(out));
  
  /* file for gtkwave */
  initial begin
    $dumpfile("____gtkwave____STRUCTURAL____.vcd");
    $dumpvars(1, dut);
  end
endmodule

/*
The ripple_counter_tester module generates the reset and clock signals for testing.
It also prints out, on stdout, the output and inputs of the ripple_counter module.

TYPE      |NAME       |WIDTH    |DESCRIPTION       
-----------------------------------------------------------------------------------
output    |resetOut   |1 bit    |The generated reset signal for testing.
output    |clkOut     |1 bit    |The genereated clk signal for testing.
input     |out        |4 bit    |The output signal used for printing to stdout.
 */
module ripple_counter_tester(resetOut, clkOut, out);
	/* Defining the output/input ports */
	output reg resetOut, clkOut;
	input[3:0] out;

	/* Delay Constant */
	parameter DELAY = 10;
	integer i;

	/* Display information of ports to stdout */
	initial begin
		$display("\t resetOut \t clkOut \t out ");
		$monitor("\t %b\t\t %b \t\t %d", resetOut, clkOut, out);
	end
	  
	parameter clk_period = 1000;
	initial clkOut = 1;
	always begin
		#(clk_period/2);
		clkOut = ~clkOut;
	end 

	initial begin
		resetOut <= 0; 			@(posedge clkOut);
		resetOut <= 1; 			@(posedge clkOut);
		
		for(i = 0; i < 26; i = i + 1) begin
			@(posedge clkOut);
		end
		
		$finish;
	end
  
endmodule

Project_1/01_counter_structural/01_counter_structural__/____gtkwave____STRUCTURAL____.vcd
$date
	Mon Jan 11 14:51:36 2016
$end
$version
	Icarus Verilog
$end
$timescale
	1s
$end
$scope module ripple_counter_testbench $end
$scope module dut $end
$var wire 1 ! reset $end
$var wire 4 " out [3:0] $end
$var wire 4 # inv_out [3:0] $end
$var wire 1 $ clk $end
$upscope $end
$upscope $end
$enddefinitions $end
#0
$dumpvars
0$
b1111 #
b0 "
0!
$end
#10
1$
#20
0$
#30
1$
#40
0$
#50
1$
#60
0$
#70
1$
#80
0$
#90
1$
#100
0$
1!
#110
b0 #
b1111 "
1$
#120
0$
#130
b1 #
b1110 "
1$
#140
0$
#150
b10 #
b1101 "
1$
#160
0$
#170
b11 #
b1100 "
1$
#180
0$
#190
b100 #
b1011 "
1$
#200
0$
#210
b101 #
b1010 "
1$
#220
0$
#230
b110 #
b1001 "
1$
#240
0$
#250
b111 #
b1000 "
1$
#260
0$
#270
b1000 #
b111 "
1$
#280
0$
#290
b1001 #
b110 "
1$
#300
0$
#310
b1010 #
b101 "
1$
#320
0$
#330
b1011 #
b100 "
1$
#340
0$
#350
b1100 #
b11 "
1$
#360
0$
#370
b1101 #
b10 "
1$
#380
0$
#390
b1110 #
b1 "
1$
#400
0$
#410
b1111 #
b0 "
1$
#420
0$
#430
b0 #
b1111 "
1$
#440
0$
#450
b1 #
b1110 "
1$
#460
0$
#470
b10 #
b1101 "
1$
#480
0$
#490
b11 #
b1100 "
1$
#500
0$
#510
b100 #
b1011 "
1$
#520
0$
#530
b101 #
b1010 "
1$
#540
0$
#550
b110 #
b1001 "
1$
#560
0$
#570
b111 #
b1000 "
1$
#580
0$
#590
b1000 #
b111 "
1$
#600
b1111 #
b0 "
0$
0!
#610
1$
#620
0$
#630
1$
#640
0$
#650
1$
#660
0$
#670
1$
#680
0$
#690
1$
#700
0$
1!
#710
b0 #
b1111 "
1$
#720
0$
#730
b1 #
b1110 "
1$
#740
0$
#750
b10 #
b1101 "
1$
#760
0$
#770
b11 #
b1100 "
1$
#780
0$
#790
b100 #
b1011 "
1$
#800
0$
#810
b101 #
b1010 "
1$
#820
0$
#830
b110 #
b1001 "
1$
#840
0$
#850
b111 #
b1000 "
1$
#860
0$
#870
b1000 #
b111 "
1$
#880
0$
#890
b1001 #
b110 "
1$
