Project_1/01_counter_structural/01_counter_structural__/ripple_counter.v
/*
The ripple_counter() module is a 4-bit down counter implemented using data flow.
@ author    Denny Ly
@ date      2016.01.07
@ version   Project 1.1 =========== < 4-bit Ripple Down Counter [Structural] >

TYPE      |NAME       |WIDTH    |DESCRIPTION       
-----------------------------------------------------------------------------------
output    |out        |4 bit    |The 4-bit output, counts from 15 to 0 in decimal.
input     |reset      |1 bit    |The reset signal (active low).
input     |clk        |1 bit    |The clock for the system.

*/
module ripple_counter(out, reset, clk);
	input reset, clk;
	output[3:0] out;
	wire[3:0] inv_out;
	
	DFlipFlop flip3 (.q(out[3]), .qBar(inv_out[3]), .D(inv_out[3]), .clk(out[2]), .rst(reset));
	DFlipFlop flip2 (.q(out[2]), .qBar(inv_out[2]), .D(inv_out[2]), .clk(out[1]), .rst(reset));
	DFlipFlop flip1 (.q(out[1]), .qBar(inv_out[1]), .D(inv_out[1]), .clk(out[0]), .rst(reset));
	DFlipFlop flip0 (.q(out[0]), .qBar(inv_out[0]), .D(inv_out[0]), .clk(clk), .rst(reset));
endmodule


/*
The DFlipFlop module is a D_Flip_Flop.  The code was given by James K. Peckol for EE371.

TYPE      |NAME       |WIDTH    |DESCRIPTION       
-----------------------------------------------------------------------------------
output    |q          |1 bit    |The present state.
output    |qBar       |1 bit    |The inverted present state.
input     |D          |1 bit    |The new state.
input     |clk        |1 bit    |The clock for the system.
input     |rst        |1 bit    |The reset signal (active low).
 */
module DFlipFlop(q, qBar, D, clk, rst);

  /* Defining the output/input ports */
  input D, clk, rst;
  output q, qBar;
  reg q;
  
  /* retrieve inverted output */
  not n1 (qBar, q);
  
  /* update the present state with the next state */
  always@ (negedge rst or posedge clk) begin
  if(!rst)
    q <= 0;
  else
    q = D;
  end
  
endmodule

/* ---------------------------------------------------------------------------------------- */
/* ------------------------------------TEST BENCH------------------------------------------ */
/* ---------------------------------------------------------------------------------------- */

/*
The ripple_counter_testbench module tests the ripple_counter module. 
*/
module ripple_counter_testbench();
  /* Wires for testing */
  wire[3:0] out;
  wire reset, clk;
  
  /* declare instance of count_down module */
  ripple_counter dut (.out(out), .reset(reset), .clk(clk));
  
  /* declare instance of test module */
  ripple_counter_tester rippleTest (.resetOut(reset), .clkOut(clk), .out(out));
  
  /* file for gtkwave */
  initial begin
    $dumpfile("____gtkwave____STRUCTURAL____.vcd");
    $dumpvars(1, dut);
  end
endmodule

/*
The ripple_counter_tester module generates the reset and clock signals for testing.
It also prints out, on stdout, the output and inputs of the ripple_counter module.

TYPE      |NAME       |WIDTH    |DESCRIPTION       
-----------------------------------------------------------------------------------
output    |resetOut   |1 bit    |The generated reset signal for testing.
output    |clkOut     |1 bit    |The genereated clk signal for testing.
input     |out        |4 bit    |The output signal used for printing to stdout.
 */
module ripple_counter_tester(resetOut, clkOut, out);
	/* Defining the output/input ports */
	output reg resetOut, clkOut;
	input[3:0] out;

	/* Delay Constant */
	parameter DELAY = 10;
	integer i;

	/* Display information of ports to stdout */
	initial begin
		$display("\t resetOut \t clkOut \t out ");
		$monitor("\t %b\t\t %b \t\t %d", resetOut, clkOut, out);
	end
	  
	parameter clk_period = 1000;
	initial clkOut = 1;
	always begin
		#(clk_period/2);
		clkOut = ~clkOut;
	end 

	initial begin
		resetOut <= 0; 			@(posedge clkOut);
		resetOut <= 1; 			@(posedge clkOut);
		
		for(i = 0; i < 26; i = i + 1) begin
			@(posedge clkOut);
		end
		
		$finish;
	end
  
endmodule

Project_1/01_counter_structural/01_counter_structural__/____gtkwave____STRUCTURAL____.vcd
$date
	Sat Jan 09 17:26:49 2016
$end
$version
	Icarus Verilog
$end
$timescale
	1s
$end
$scope module ripple_counter_testbench $end
$scope module dut $end
$var wire 1 ! reset $end
$var wire 4 " out [3:0] $end
$var wire 4 # inv_out [3:0] $end
$var wire 1 $ clk $end
$upscope $end
$upscope $end
$enddefinitions $end
#0
$dumpvars
1$
b1111 #
b0 "
0!
$end
#500
0$
#1000
1!
1$
#1500
0$
#2000
b0 #
b1111 "
1$
#2500
0$
#3000
b1 #
b1110 "
1$
#3500
0$
#4000
b10 #
b1101 "
1$
#4500
0$
#5000
b11 #
b1100 "
1$
#5500
0$
#6000
b100 #
b1011 "
1$
#6500
0$
#7000
b101 #
b1010 "
1$
#7500
0$
#8000
b110 #
b1001 "
1$
#8500
0$
#9000
b111 #
b1000 "
1$
#9500
0$
#10000
b1000 #
b111 "
1$
#10500
0$
#11000
b1001 #
b110 "
1$
#11500
0$
#12000
b1010 #
b101 "
1$
#12500
0$
#13000
b1011 #
b100 "
1$
#13500
0$
#14000
b1100 #
b11 "
1$
#14500
0$
#15000
b1101 #
b10 "
1$
#15500
0$
#16000
b1110 #
b1 "
1$
#16500
0$
#17000
b1111 #
b0 "
1$
#17500
0$
#18000
b0 #
b1111 "
1$
#18500
0$
#19000
b1 #
b1110 "
1$
#19500
0$
#20000
b10 #
b1101 "
1$
#20500
0$
#21000
b11 #
b1100 "
1$
#21500
0$
#22000
b100 #
b1011 "
1$
#22500
0$
#23000
b101 #
b1010 "
1$
#23500
0$
#24000
b110 #
b1001 "
1$
#24500
0$
#25000
b111 #
b1000 "
1$
#25500
0$
#26000
b1000 #
b111 "
1$
#26500
0$
#27000
b1001 #
b110 "
1$
#27500
0$
#28000
b1010 #
b101 "
1$
